[
  {
    "text": "BERT",
    "type": "method",
    "char_interval": {
      "start_pos": 28,
      "end_pos": 32
    },
    "attributes": {},
    "sentence_context": "In this section, we present BERT fine-tuning results on 11 NLP tasks.",
    "sentence_index": 0,
    "section": "Experiments"
  },
  {
    "text": "NLP tasks",
    "type": "task",
    "char_interval": {
      "start_pos": 59,
      "end_pos": 68
    },
    "attributes": {},
    "sentence_context": "In this section, we present BERT fine-tuning results on 11 NLP tasks.",
    "sentence_index": 0,
    "section": "Experiments"
  }
]